apiritif/__init__.py
apiritif/__main__.py
apiritif/action_plugins.py
apiritif/csv.py
apiritif/http.py
apiritif/loadgen.py
apiritif/pytest_plugin.py
apiritif/samples.py
apiritif/ssl_adapter.py
apiritif/store.py
apiritif/thread.py
apiritif/utilities.py
apiritif/utils.py
apiritif-1.1.3.dist-info/LICENSE
apiritif-1.1.3.dist-info/METADATA
apiritif-1.1.3.dist-info/WHEEL
apiritif-1.1.3.dist-info/entry_points.txt
apiritif-1.1.3.dist-info/top_level.txt
apiritif-1.1.3.dist-info/RECORD
