Metadata-Version: 2.1
Name: apiritif
Version: 1.1.3
Summary: Python framework for API testing
Home-page: https://github.com/Blazemeter/apiritif
Author: Dmitri Pribysh
Author-email: pribysh@blazemeter.com
License: Apache 2.0
Download-URL: https://github.com/Blazemeter/apiritif
Platform: UNKNOWN
License-File: LICENSE
